onellmclient/__init__.py
onellmclient/client.py
onellmclient/types.py
onellmclient/provider/anthropic.py
onellmclient/provider/deepseek.py
onellmclient/provider/gemini.py
onellmclient/provider/openai.py
onellmclient/provider/xai.py
onellmclient-0.1.4.dist-info/METADATA
onellmclient-0.1.4.dist-info/WHEEL
onellmclient-0.1.4.dist-info/licenses/LICENSE
onellmclient-0.1.4.dist-info/RECORD
