Metadata-Version: 2.4
Name: onellmclient
Version: 0.1.4
Summary: A unified Python client to normalize interfaces across major LLM providers (OpenAI, Anthropic, Gemini, DeepSeek, xAI).
Author-email: Elevioux <elevioux@live.com>
License: MIT License
License-File: LICENSE
Keywords: anthropic,client,deepseek,gemini,grok,llm,openai,sdk,xai
Classifier: License :: OSI Approved :: MIT License
Classifier: Operating System :: OS Independent
Classifier: Programming Language :: Python :: 3
Classifier: Programming Language :: Python :: 3 :: Only
Classifier: Programming Language :: Python :: 3.10
Classifier: Programming Language :: Python :: 3.11
Classifier: Programming Language :: Python :: 3.12
Requires-Python: >=3.10
Requires-Dist: anthropic>=0.68.0
Requires-Dist: google-genai>=1.38.0
Requires-Dist: openai>=1.109.1
Provides-Extra: publish
Requires-Dist: build<2.0.0,>=1.2.1; extra == 'publish'
Requires-Dist: twine<6.0.0,>=5.1.1; extra == 'publish'
Provides-Extra: test
Requires-Dist: pytest<9.0.0,>=8.4.2; extra == 'test'
Requires-Dist: python-dotenv<2.0,>=1.1.1; extra == 'test'
